sto_libdata/__init__.py
sto_libdata/connection/__init__.py
sto_libdata/connection/connection_handler.py
sto_libdata/connection/database_connection.py
sto_libdata/dataframe_handling/__init__.py
sto_libdata/dataframe_handling/data_manipulation.py
sto_libdata/dataframe_handling/dataframe_handler.py
sto_libdata/dataframe_handling/normalization.py
sto_libdata/dataframe_handling/pushable_dataframe.py
sto_libdata/dataframe_handling/shared.py
sto_libdata/exceptions/__init__.py
sto_libdata/exceptions/exceptions.py
sto_libdata-1.1.3.dist-info/licenses/LICENSE
sto_libdata-1.1.3.dist-info/METADATA
sto_libdata-1.1.3.dist-info/WHEEL
sto_libdata-1.1.3.dist-info/top_level.txt
sto_libdata-1.1.3.dist-info/RECORD
