Metadata-Version: 2.4
Name: sto-libdata
Version: 1.1.3
Summary: STO's library for handling data.
Author-email: Frank William Hammond Espinosa <frank.hammond@fueib.org>
Project-URL: Source, https://github.com/Frankwii/sto_libdata
Keywords: sto
Requires-Python: >=3.12
License-File: LICENSE
Requires-Dist: pandas
Requires-Dist: sqlalchemy
Requires-Dist: dotenv
Requires-Dist: pyodbc
Dynamic: license-file
